codigo/__init__.py
codigo/admin.py
codigo/apps.py
codigo/models.py
codigo/serializers.py
codigo/tests.py
codigo/urls.py
codigo/views.py
django_verification_code-0.2.4.dist-info/LICENSE
django_verification_code-0.2.4.dist-info/METADATA
django_verification_code-0.2.4.dist-info/WHEEL
django_verification_code-0.2.4.dist-info/top_level.txt
django_verification_code-0.2.4.dist-info/RECORD
